thehive4py/__init__.py
thehive4py/__version__.py
thehive4py/client.py
thehive4py/errors.py
thehive4py/helpers.py
thehive4py/py.typed
thehive4py/session.py
thehive4py/endpoints/__init__.py
thehive4py/endpoints/_base.py
thehive4py/endpoints/alert.py
thehive4py/endpoints/case.py
thehive4py/endpoints/case_template.py
thehive4py/endpoints/comment.py
thehive4py/endpoints/cortex.py
thehive4py/endpoints/custom_field.py
thehive4py/endpoints/misp.py
thehive4py/endpoints/observable.py
thehive4py/endpoints/observable_type.py
thehive4py/endpoints/organisation.py
thehive4py/endpoints/page_template.py
thehive4py/endpoints/procedure.py
thehive4py/endpoints/profile.py
thehive4py/endpoints/query.py
thehive4py/endpoints/task.py
thehive4py/endpoints/task_log.py
thehive4py/endpoints/timeline.py
thehive4py/endpoints/user.py
thehive4py/query/__init__.py
thehive4py/query/filters.py
thehive4py/query/page.py
thehive4py/query/sort.py
thehive4py/types/__init__.py
thehive4py/types/alert.py
thehive4py/types/attachment.py
thehive4py/types/case.py
thehive4py/types/case_template.py
thehive4py/types/comment.py
thehive4py/types/cortex.py
thehive4py/types/custom_field.py
thehive4py/types/misp.py
thehive4py/types/observable.py
thehive4py/types/observable_type.py
thehive4py/types/organisation.py
thehive4py/types/page.py
thehive4py/types/page_template.py
thehive4py/types/procedure.py
thehive4py/types/profile.py
thehive4py/types/share.py
thehive4py/types/task.py
thehive4py/types/task_log.py
thehive4py/types/timeline.py
thehive4py/types/user.py
thehive4py-2.0.2.dist-info/licenses/LICENSE
thehive4py-2.0.2.dist-info/METADATA
thehive4py-2.0.2.dist-info/WHEEL
thehive4py-2.0.2.dist-info/top_level.txt
thehive4py-2.0.2.dist-info/RECORD
