Metadata-Version: 2.4
Name: thehive4py
Version: 2.0.2
Summary: Python client for TheHive5
Author-email: Szabolcs Antal <antalszabolcs01@gmail.com>
License-Expression: MIT
Keywords: thehive5,api,client
Classifier: Development Status :: 5 - Production/Stable
Classifier: Intended Audience :: Developers
Classifier: Intended Audience :: Information Technology
Classifier: Natural Language :: English
Classifier: Programming Language :: Python :: 3.9
Classifier: Programming Language :: Python :: 3.10
Classifier: Programming Language :: Python :: 3.11
Classifier: Programming Language :: Python :: 3.12
Classifier: Programming Language :: Python :: 3.13
Requires-Python: >=3.9
License-File: LICENSE
Requires-Dist: requests~=2.27
Requires-Dist: typing_extensions==4.*
Provides-Extra: audit
Requires-Dist: bandit; extra == "audit"
Requires-Dist: pip-audit; extra == "audit"
Provides-Extra: build
Requires-Dist: build; extra == "build"
Requires-Dist: twine; extra == "build"
Provides-Extra: docs
Requires-Dist: mkdocs; extra == "docs"
Requires-Dist: mkdocs-material; extra == "docs"
Requires-Dist: mkdocstrings-python; extra == "docs"
Requires-Dist: mike; extra == "docs"
Provides-Extra: lint
Requires-Dist: mypy; extra == "lint"
Requires-Dist: ruff; extra == "lint"
Requires-Dist: pre-commit; extra == "lint"
Provides-Extra: test
Requires-Dist: pytest; extra == "test"
Requires-Dist: pytest-cov; extra == "test"
Provides-Extra: dev
Requires-Dist: thehive4py[audit,build,docs,lint,test]; extra == "dev"
Requires-Dist: nox; extra == "dev"
Dynamic: license-file
